scheduledexecutor/__init__.py
scheduledexecutor/base.py
scheduledexecutor/process.py
scheduledexecutor/thread.py
scheduledexecutor-0.0.1.dist-info/LICENSE
scheduledexecutor-0.0.1.dist-info/METADATA
scheduledexecutor-0.0.1.dist-info/WHEEL
scheduledexecutor-0.0.1.dist-info/top_level.txt
scheduledexecutor-0.0.1.dist-info/RECORD
