Metadata-Version: 2.1
Name: scheduledexecutor
Version: 0.0.1
Summary: scheduledexecutor
Home-page: https://github.com/delegacy/scheduledexecutor
Author: YoungTae Seok
Author-email: delegacy@gmail.com
License: UNKNOWN
Project-URL: Bug Tracker, https://github.com/delegacy/scheduledexecutor/issues
Platform: UNKNOWN
Classifier: Programming Language :: Python :: 3
Classifier: License :: OSI Approved :: MIT License
Classifier: Operating System :: OS Independent
Requires-Python: >=3.7
License-File: LICENSE
